PyCPP-0.0.6.data/scripts/pycpp.py
pycpp/__init__.py
pycpp/FuncParser/__init__.py
PyCPP-0.0.6.dist-info/LICENSE
PyCPP-0.0.6.dist-info/METADATA
PyCPP-0.0.6.dist-info/WHEEL
PyCPP-0.0.6.dist-info/top_level.txt
PyCPP-0.0.6.dist-info/RECORD
