Metadata-Version: 2.1
Name: PyCPP
Version: 0.0.6
Summary: PyCPP is a simple tool for wrapping and using C++ functions and libraries.
Home-page: https://github.com/commander07/PyCPP
Author: Commander07
Author-email: author@example.com
License: UNKNOWN
Platform: UNKNOWN
Requires-Python: >=3.6
